syndicate/__init__.py
syndicate/actor.py
syndicate/dataflow.py
syndicate/dataspace.py
syndicate/during.py
syndicate/gatekeeper.py
syndicate/idgen.py
syndicate/mapset.py
syndicate/metapy.py
syndicate/patterns.py
syndicate/relay.py
syndicate/schema.py
syndicate/transport.py
syndicate/protocols/Makefile
syndicate/protocols/schema-bundle.bin
syndicate/protocols/schemas/dataspace.prs
syndicate/protocols/schemas/dataspacePatterns.prs
syndicate/protocols/schemas/gatekeeper.prs
syndicate/protocols/schemas/http.prs
syndicate/protocols/schemas/noise.prs
syndicate/protocols/schemas/protocol.prs
syndicate/protocols/schemas/service.prs
syndicate/protocols/schemas/stdenv.prs
syndicate/protocols/schemas/stream.prs
syndicate/protocols/schemas/sturdy.prs
syndicate/protocols/schemas/tcp.prs
syndicate/protocols/schemas/timer.prs
syndicate/protocols/schemas/trace.prs
syndicate/protocols/schemas/transportAddress.prs
syndicate/protocols/schemas/worker.prs
syndicate_py-0.19.3.dist-info/METADATA
syndicate_py-0.19.3.dist-info/WHEEL
syndicate_py-0.19.3.dist-info/top_level.txt
syndicate_py-0.19.3.dist-info/RECORD
