Metadata-Version: 2.4
Name: syndicate-py
Version: 0.19.3
Summary: Syndicated Actor model and Syndicate network protocol for Python 3
Author-email: Tony Garnock-Jones <tonyg@leastfixedpoint.com>
License: GPL-3.0-or-later
Project-URL: Homepage, https://git.syndicate-lang.org/syndicate-lang/syndicate-py
Project-URL: Issues, https://git.syndicate-lang.org/syndicate-lang/syndicate-py/issues
Classifier: Development Status :: 3 - Alpha
Classifier: Intended Audience :: Developers
Classifier: Topic :: Software Development :: Libraries :: Python Modules
Classifier: License :: OSI Approved :: GNU General Public License v3 or later (GPLv3+)
Classifier: Programming Language :: Python :: 3
Requires-Python: <4,>=3.6
Requires-Dist: preserves>=0.996.3
Provides-Extra: dev
Requires-Dist: build; extra == "dev"
Requires-Dist: twine; extra == "dev"
